labypy/Cape.py
labypy/Dragon.py
labypy/Eyes.py
labypy/Fisher.py
labypy/Halo.py
labypy/Hand.py
labypy/Hat.py
labypy/Horns.py
labypy/Wings.py
labypy/__init__.py
labypy-1.0.dist-info/LICENSE
labypy-1.0.dist-info/METADATA
labypy-1.0.dist-info/WHEEL
labypy-1.0.dist-info/top_level.txt
labypy-1.0.dist-info/RECORD
