Metadata-Version: 2.1
Name: labypy
Version: 1.0
Summary: A Labymod Cosmetics Library
Home-page: UNKNOWN
Author: Zyking
Author-email: UNKNOWN
License: MIT
Platform: UNKNOWN
Requires-Dist: requests
